{
  "a32_intake_requested": false,
  "a32_review_eligibility_assessment": {
    "a32_review_recommendation": "READY_FOR_A32_CONTROL_DEPENDENCE_REVIEW_CANDIDATE_ONLY",
    "a32_write_performed": false,
    "a33_write_performed": false,
    "action1_neutral_observations": 2,
    "action1_positive_contexts": 5,
    "action3_neutral_contexts": 3,
    "assessment_id": "sage6f::a32_review_eligibility_assessment::001",
    "candidate_key": "control_dependent_local_patch::wa30-ee6fef47::ACTION2::ACTION1_vs_ACTION3",
    "candidate_mechanism_family": "control_dependent_local_patch_change_candidate",
    "candidate_status": "CONTROL_DEPENDENT_MULTI_BUDGET_WITH_REPLICATED_NEUTRAL_EXCEPTION_CANDIDATE_ONLY",
    "context_clusters": 6,
    "control_actions": [
      "ACTION1",
      "ACTION3"
    ],
    "distinct_control_actions": 2,
    "eligibility_counted_as_a32_decision": false,
    "eligibility_requirements": {
      "action1_positive_pattern_spans_all_budgets": true,
      "action3_neutral_pattern_spans_all_budgets": true,
      "all_context_boundaries_preserved": true,
      "all_sage6e_followups_executed_exactly": true,
      "candidate_claim_reformulated_as_control_dependent": true,
      "minimum_distinct_control_actions_reached": true,
      "minimum_paired_control_contexts_reached": true,
      "minimum_raw_positive_contexts_reached": true,
      "neutral_exception_has_exact_replication": true,
      "no_negative_effect_events": true,
      "paired_control_effect_gap_is_stable_positive": true,
      "paired_controls_cover_all_source_budgets": true,
      "source_sage6c_gate_passed": true,
      "source_sage6e_gate_passed": true
    },
    "game_id": "wa30-ee6fef47",
    "metric": "local_patch_before_after",
    "missing_eligibility_requirements": [],
    "negative_effect_events": 0,
    "paired_control_budgets": [
      50,
      150,
      300
    ],
    "paired_control_contexts": 3,
    "paired_control_effect_gap_spread": 0.0,
    "paired_control_effect_gaps": [
      32.0,
      32.0,
      32.0
    ],
    "raw_contradiction_events": 0,
    "raw_events_counted_as_scientific_support": false,
    "raw_neutral_events": 5,
    "raw_support_events": 5,
    "ready_for_A32_review": true,
    "ready_for_A32_review_is_not_confirmation": true,
    "ready_for_A32_review_is_not_verdict": true,
    "recommended_a32_review_scope": {
      "must_not_review_as": "STANDALONE_UNCONDITIONAL_ACTION2_EFFECT",
      "review_claim": "ACTION2 local-patch contrast is control-dependent: positive versus ACTION1 but neutral versus ACTION3 in paired wa30 contexts.",
      "scope_context_cluster_ids": [
        "sage6c::context_cluster::001",
        "sage6c::context_cluster::002",
        "sage6c::context_cluster::003",
        "sage6c::context_cluster::004",
        "sage6c::context_cluster::005",
        "sage6c::context_cluster::006"
      ],
      "scope_controls": [
        "ACTION1",
        "ACTION3"
      ],
      "scope_game_id": "wa30-ee6fef47"
    },
    "replicated_neutral_contexts": 1,
    "required_next_step": "A32_SCIENTIFIC_REVIEW_OF_CONTROL_DEPENDENT_CANDIDATE",
    "revision_performed": false,
    "revision_status": "CANDIDATE_ONLY",
    "source_budgets": [
      50,
      150,
      300
    ],
    "status": "UNRESOLVED",
    "support": 0,
    "target_action": "ACTION2",
    "truth_status": "NOT_EVALUATED_BY_SAGE_6F",
    "wrong_confirmations": 0
  },
  "a32_review_eligibility_counted_as_a32_decision": false,
  "a32_write_performed": false,
  "a33_write_performed": false,
  "candidate_a32_review_frontiers": [
    {
      "a32_intake_requested": false,
      "a32_review_questions": [
        "IS_ACTION1_A_VALID_LOWER_EFFECT_COMPARATOR_IN_THE_RECORDED_CONTEXTS",
        "DOES_ACTION3_EQUIVALENCE_MAKE_THE_STANDALONE_ACTION2_CLAIM_NON_IDENTIFIABLE",
        "WHAT_WA30_CONTEXT_SCOPE_CAN_BE_SCIENTIFICALLY_JUSTIFIED"
      ],
      "a32_write_performed": false,
      "a33_write_performed": false,
      "candidate_claim": {
        "must_not_review_as": "STANDALONE_UNCONDITIONAL_ACTION2_EFFECT",
        "review_claim": "ACTION2 local-patch contrast is control-dependent: positive versus ACTION1 but neutral versus ACTION3 in paired wa30 contexts.",
        "scope_context_cluster_ids": [
          "sage6c::context_cluster::001",
          "sage6c::context_cluster::002",
          "sage6c::context_cluster::003",
          "sage6c::context_cluster::004",
          "sage6c::context_cluster::005",
          "sage6c::context_cluster::006"
        ],
        "scope_controls": [
          "ACTION1",
          "ACTION3"
        ],
        "scope_game_id": "wa30-ee6fef47"
      },
      "candidate_key": "control_dependent_local_patch::wa30-ee6fef47::ACTION2::ACTION1_vs_ACTION3",
      "candidate_mechanism_family": "control_dependent_local_patch_change_candidate",
      "context_cluster_ids": [
        "sage6c::context_cluster::001",
        "sage6c::context_cluster::002",
        "sage6c::context_cluster::003",
        "sage6c::context_cluster::004",
        "sage6c::context_cluster::005",
        "sage6c::context_cluster::006"
      ],
      "control_actions": [
        "ACTION1",
        "ACTION3"
      ],
      "control_conditioned_effect_group_ids": [
        "sage6f::control_conditioned_effect_group::001",
        "sage6f::control_conditioned_effect_group::002",
        "sage6f::control_conditioned_effect_group::003"
      ],
      "frontier_counted_as_revision": false,
      "frontier_id": "sage6f::candidate_a32_control_dependence_frontier::001",
      "game_id": "wa30-ee6fef47",
      "metric": "local_patch_before_after",
      "missing_eligibility_requirements": [],
      "paired_control_comparison_ids": [
        "sage6f::paired_control_comparison::001",
        "sage6f::paired_control_comparison::002",
        "sage6f::paired_control_comparison::003"
      ],
      "raw_events_counted_as_support": false,
      "ready_for_A32_review": true,
      "ready_for_A32_review_is_not_confirmation": true,
      "ready_for_A32_review_is_not_verdict": true,
      "revision_performed": false,
      "revision_status": "CANDIDATE_ONLY",
      "source_assessment_id": "sage6f::a32_review_eligibility_assessment::001",
      "status": "UNRESOLVED",
      "support": 0,
      "target_action": "ACTION2",
      "truth_status": "NOT_EVALUATED_BY_SAGE_6F",
      "wrong_confirmations": 0
    }
  ],
  "config": {
    "a32_review_eligibility_thresholds": {
      "all_source_budgets_must_have_paired_controls": true,
      "maximum_negative_effect_events": 0,
      "minimum_distinct_control_actions": 2,
      "minimum_paired_control_contexts": 3,
      "minimum_raw_positive_contexts": 3,
      "neutral_exception_must_have_exact_replication": true
    },
    "artifacts_not_modified": [
      "SAGE.6e",
      "SAGE.6d",
      "SAGE.6c",
      "SAGE.6b",
      "SAGE.6a",
      "SAGE.6",
      "SAGE.5",
      "A32",
      "A33",
      "M2",
      "M3",
      "A40",
      "P2"
    ],
    "consolidation_policy": {
      "a32_review_eligibility_is_not_a32_decision": true,
      "a32_write_performed": false,
      "a33_write_performed": false,
      "control_action_identity_is_immutable": true,
      "control_conditioned_groups_are_comparison_indexes_only": true,
      "cross_context_merge_allowed": false,
      "cross_control_effect_merge_allowed": false,
      "one_cluster_per_sage6c_context_snapshot_hash": true,
      "paired_control_comparison_is_not_scientific_verdict": true,
      "raw_events_are_not_scientific_support": true,
      "same_context_replications_are_linked_not_independent": true
    },
    "execution_performed": false,
    "inputs_read": [
      "SAGE.6c",
      "SAGE.6e"
    ],
    "schema_version": "sage.second_unknown_game_control_dependence_consolidation.v1",
    "source_sage6c_path": "diagnostics\\sage\\sage6c_second_unknown_game_event_consolidation.json",
    "source_sage6e_path": "diagnostics\\sage\\sage6e_second_unknown_game_followup_execution.json"
  },
  "confirmation_performed": false,
  "context_cluster_manifest": [
    {
      "a32_write_performed": false,
      "a33_write_performed": false,
      "budgets": [
        50
      ],
      "candidate_status": "ACTION1_REPLICATED_NEUTRAL_CONTEXT_CANDIDATE_ONLY",
      "cluster_status_counted_as_scientific_verdict": false,
      "context_cluster_id": "sage6c::context_cluster::001",
      "context_preserved": true,
      "context_snapshot_hash": "{\"digest\":\"762cdd46923302d2\",\"game_state\":\"NOT_FINISHED\",\"levels_completed\":0,\"shape\":[64,64]}",
      "control_actions": [
        "ACTION1"
      ],
      "cross_context_merge_performed": false,
      "cross_control_effect_merge_performed": false,
      "effects_by_control": {
        "ACTION1": [
          0.0,
          0.0
        ]
      },
      "game_id": "wa30-ee6fef47",
      "independent_contexts": 1,
      "neutral_context_replication_verified": true,
      "observation_ids": [
        "sage6f::control_observation::001",
        "sage6f::control_observation::002"
      ],
      "observations": 2,
      "paired_control_context": false,
      "revision_performed": false,
      "revision_status": "CANDIDATE_ONLY",
      "same_context_replications": 1,
      "source_request_ids": [
        "m2m3::sage6a::live_mini_frontier::050::0012"
      ],
      "source_stages": [
        "SAGE.6c",
        "SAGE.6e"
      ],
      "source_steps": [
        12
      ],
      "status": "UNRESOLVED",
      "support": 0,
      "truth_status": "NOT_EVALUATED_BY_SAGE_6F",
      "wrong_confirmations": 0
    },
    {
      "a32_write_performed": false,
      "a33_write_performed": false,
      "budgets": [
        50
      ],
      "candidate_status": "PAIRED_ACTION1_ACTION3_CONTROL_DEPENDENT_CONTEXT_CANDIDATE_ONLY",
      "cluster_status_counted_as_scientific_verdict": false,
      "context_cluster_id": "sage6c::context_cluster::002",
      "context_preserved": true,
      "context_snapshot_hash": "{\"digest\":\"cee711e164dcf771\",\"game_state\":\"NOT_FINISHED\",\"levels_completed\":0,\"shape\":[64,64]}",
      "control_actions": [
        "ACTION1",
        "ACTION3"
      ],
      "cross_context_merge_performed": false,
      "cross_control_effect_merge_performed": false,
      "effects_by_control": {
        "ACTION1": [
          32.0
        ],
        "ACTION3": [
          0.0
        ]
      },
      "game_id": "wa30-ee6fef47",
      "independent_contexts": 1,
      "neutral_context_replication_verified": false,
      "observation_ids": [
        "sage6f::control_observation::003",
        "sage6f::control_observation::004"
      ],
      "observations": 2,
      "paired_control_context": true,
      "revision_performed": false,
      "revision_status": "CANDIDATE_ONLY",
      "same_context_replications": 0,
      "source_request_ids": [
        "m2m3::sage6a::live_mini_frontier::050::0048"
      ],
      "source_stages": [
        "SAGE.6c",
        "SAGE.6e"
      ],
      "source_steps": [
        48
      ],
      "status": "UNRESOLVED",
      "support": 0,
      "truth_status": "NOT_EVALUATED_BY_SAGE_6F",
      "wrong_confirmations": 0
    },
    {
      "a32_write_performed": false,
      "a33_write_performed": false,
      "budgets": [
        150
      ],
      "candidate_status": "PAIRED_ACTION1_ACTION3_CONTROL_DEPENDENT_CONTEXT_CANDIDATE_ONLY",
      "cluster_status_counted_as_scientific_verdict": false,
      "context_cluster_id": "sage6c::context_cluster::003",
      "context_preserved": true,
      "context_snapshot_hash": "{\"digest\":\"2fd24ab52132f6bc\",\"game_state\":\"NOT_FINISHED\",\"levels_completed\":0,\"shape\":[64,64]}",
      "control_actions": [
        "ACTION1",
        "ACTION3"
      ],
      "cross_context_merge_performed": false,
      "cross_control_effect_merge_performed": false,
      "effects_by_control": {
        "ACTION1": [
          32.0
        ],
        "ACTION3": [
          0.0
        ]
      },
      "game_id": "wa30-ee6fef47",
      "independent_contexts": 1,
      "neutral_context_replication_verified": false,
      "observation_ids": [
        "sage6f::control_observation::005",
        "sage6f::control_observation::006"
      ],
      "observations": 2,
      "paired_control_context": true,
      "revision_performed": false,
      "revision_status": "CANDIDATE_ONLY",
      "same_context_replications": 0,
      "source_request_ids": [
        "m2m3::sage6a::live_mini_frontier::150::0132"
      ],
      "source_stages": [
        "SAGE.6c",
        "SAGE.6e"
      ],
      "source_steps": [
        132
      ],
      "status": "UNRESOLVED",
      "support": 0,
      "truth_status": "NOT_EVALUATED_BY_SAGE_6F",
      "wrong_confirmations": 0
    },
    {
      "a32_write_performed": false,
      "a33_write_performed": false,
      "budgets": [
        150
      ],
      "candidate_status": "UNPAIRED_ACTION1_POSITIVE_CONTEXT_CANDIDATE_ONLY",
      "cluster_status_counted_as_scientific_verdict": false,
      "context_cluster_id": "sage6c::context_cluster::004",
      "context_preserved": true,
      "context_snapshot_hash": "{\"digest\":\"fc273c717dbdb25d\",\"game_state\":\"NOT_FINISHED\",\"levels_completed\":0,\"shape\":[64,64]}",
      "control_actions": [
        "ACTION1"
      ],
      "cross_context_merge_performed": false,
      "cross_control_effect_merge_performed": false,
      "effects_by_control": {
        "ACTION1": [
          32.0
        ]
      },
      "game_id": "wa30-ee6fef47",
      "independent_contexts": 1,
      "neutral_context_replication_verified": false,
      "observation_ids": [
        "sage6f::control_observation::007"
      ],
      "observations": 1,
      "paired_control_context": false,
      "revision_performed": false,
      "revision_status": "CANDIDATE_ONLY",
      "same_context_replications": 0,
      "source_request_ids": [
        "m2m3::sage6a::live_mini_frontier::150::0144"
      ],
      "source_stages": [
        "SAGE.6c"
      ],
      "source_steps": [
        144
      ],
      "status": "UNRESOLVED",
      "support": 0,
      "truth_status": "NOT_EVALUATED_BY_SAGE_6F",
      "wrong_confirmations": 0
    },
    {
      "a32_write_performed": false,
      "a33_write_performed": false,
      "budgets": [
        300
      ],
      "candidate_status": "PAIRED_ACTION1_ACTION3_CONTROL_DEPENDENT_CONTEXT_CANDIDATE_ONLY",
      "cluster_status_counted_as_scientific_verdict": false,
      "context_cluster_id": "sage6c::context_cluster::005",
      "context_preserved": true,
      "context_snapshot_hash": "{\"digest\":\"fd06017864128f48\",\"game_state\":\"NOT_FINISHED\",\"levels_completed\":0,\"shape\":[64,64]}",
      "control_actions": [
        "ACTION1",
        "ACTION3"
      ],
      "cross_context_merge_performed": false,
      "cross_control_effect_merge_performed": false,
      "effects_by_control": {
        "ACTION1": [
          32.0
        ],
        "ACTION3": [
          0.0
        ]
      },
      "game_id": "wa30-ee6fef47",
      "independent_contexts": 1,
      "neutral_context_replication_verified": false,
      "observation_ids": [
        "sage6f::control_observation::008",
        "sage6f::control_observation::009"
      ],
      "observations": 2,
      "paired_control_context": true,
      "revision_performed": false,
      "revision_status": "CANDIDATE_ONLY",
      "same_context_replications": 0,
      "source_request_ids": [
        "m2m3::sage6a::live_mini_frontier::300::0024"
      ],
      "source_stages": [
        "SAGE.6c",
        "SAGE.6e"
      ],
      "source_steps": [
        24
      ],
      "status": "UNRESOLVED",
      "support": 0,
      "truth_status": "NOT_EVALUATED_BY_SAGE_6F",
      "wrong_confirmations": 0
    },
    {
      "a32_write_performed": false,
      "a33_write_performed": false,
      "budgets": [
        300
      ],
      "candidate_status": "UNPAIRED_ACTION1_POSITIVE_CONTEXT_CANDIDATE_ONLY",
      "cluster_status_counted_as_scientific_verdict": false,
      "context_cluster_id": "sage6c::context_cluster::006",
      "context_preserved": true,
      "context_snapshot_hash": "{\"digest\":\"d56ee8f2b81af1e5\",\"game_state\":\"NOT_FINISHED\",\"levels_completed\":0,\"shape\":[64,64]}",
      "control_actions": [
        "ACTION1"
      ],
      "cross_context_merge_performed": false,
      "cross_control_effect_merge_performed": false,
      "effects_by_control": {
        "ACTION1": [
          32.0
        ]
      },
      "game_id": "wa30-ee6fef47",
      "independent_contexts": 1,
      "neutral_context_replication_verified": false,
      "observation_ids": [
        "sage6f::control_observation::010"
      ],
      "observations": 1,
      "paired_control_context": false,
      "revision_performed": false,
      "revision_status": "CANDIDATE_ONLY",
      "same_context_replications": 0,
      "source_request_ids": [
        "m2m3::sage6a::live_mini_frontier::300::0036"
      ],
      "source_stages": [
        "SAGE.6c"
      ],
      "source_steps": [
        36
      ],
      "status": "UNRESOLVED",
      "support": 0,
      "truth_status": "NOT_EVALUATED_BY_SAGE_6F",
      "wrong_confirmations": 0
    }
  ],
  "control_conditioned_effect_groups": [
    {
      "a32_write_performed": false,
      "a33_write_performed": false,
      "budgets": [
        50,
        150,
        300
      ],
      "comparison_index_only": true,
      "context_cluster_ids": [
        "sage6c::context_cluster::002",
        "sage6c::context_cluster::003",
        "sage6c::context_cluster::004",
        "sage6c::context_cluster::005",
        "sage6c::context_cluster::006"
      ],
      "context_snapshot_hashes": [
        "{\"digest\":\"2fd24ab52132f6bc\",\"game_state\":\"NOT_FINISHED\",\"levels_completed\":0,\"shape\":[64,64]}",
        "{\"digest\":\"cee711e164dcf771\",\"game_state\":\"NOT_FINISHED\",\"levels_completed\":0,\"shape\":[64,64]}",
        "{\"digest\":\"d56ee8f2b81af1e5\",\"game_state\":\"NOT_FINISHED\",\"levels_completed\":0,\"shape\":[64,64]}",
        "{\"digest\":\"fc273c717dbdb25d\",\"game_state\":\"NOT_FINISHED\",\"levels_completed\":0,\"shape\":[64,64]}",
        "{\"digest\":\"fd06017864128f48\",\"game_state\":\"NOT_FINISHED\",\"levels_completed\":0,\"shape\":[64,64]}"
      ],
      "control_action": "ACTION1",
      "control_effect_group_id": "sage6f::control_conditioned_effect_group::001",
      "cross_context_merge_performed": false,
      "cross_control_effect_merge_performed": false,
      "effect_direction": "positive",
      "effect_size_max": 32.0,
      "effect_size_min": 32.0,
      "effect_size_spread": 0.0,
      "effect_sizes": [
        32.0,
        32.0,
        32.0,
        32.0,
        32.0
      ],
      "game_id": "wa30-ee6fef47",
      "group_counted_as_scientific_evidence": false,
      "hypothesis_family": "local_patch_change_candidate",
      "independent_contexts": 5,
      "metric": "local_patch_before_after",
      "observation_ids": [
        "sage6f::control_observation::003",
        "sage6f::control_observation::005",
        "sage6f::control_observation::007",
        "sage6f::control_observation::008",
        "sage6f::control_observation::010"
      ],
      "observations": 5,
      "raw_contradiction_events": 0,
      "raw_neutral_events": 0,
      "raw_support_events": 5,
      "revision_performed": false,
      "revision_status": "CANDIDATE_ONLY",
      "status": "UNRESOLVED",
      "support": 0,
      "target_action": "ACTION2",
      "truth_status": "NOT_EVALUATED_BY_SAGE_6F",
      "wrong_confirmations": 0
    },
    {
      "a32_write_performed": false,
      "a33_write_performed": false,
      "budgets": [
        50
      ],
      "comparison_index_only": true,
      "context_cluster_ids": [
        "sage6c::context_cluster::001"
      ],
      "context_snapshot_hashes": [
        "{\"digest\":\"762cdd46923302d2\",\"game_state\":\"NOT_FINISHED\",\"levels_completed\":0,\"shape\":[64,64]}"
      ],
      "control_action": "ACTION1",
      "control_effect_group_id": "sage6f::control_conditioned_effect_group::002",
      "cross_context_merge_performed": false,
      "cross_control_effect_merge_performed": false,
      "effect_direction": "neutral",
      "effect_size_max": 0.0,
      "effect_size_min": 0.0,
      "effect_size_spread": 0.0,
      "effect_sizes": [
        0.0,
        0.0
      ],
      "game_id": "wa30-ee6fef47",
      "group_counted_as_scientific_evidence": false,
      "hypothesis_family": "local_patch_change_candidate",
      "independent_contexts": 1,
      "metric": "local_patch_before_after",
      "observation_ids": [
        "sage6f::control_observation::001",
        "sage6f::control_observation::002"
      ],
      "observations": 2,
      "raw_contradiction_events": 0,
      "raw_neutral_events": 2,
      "raw_support_events": 0,
      "revision_performed": false,
      "revision_status": "CANDIDATE_ONLY",
      "status": "UNRESOLVED",
      "support": 0,
      "target_action": "ACTION2",
      "truth_status": "NOT_EVALUATED_BY_SAGE_6F",
      "wrong_confirmations": 0
    },
    {
      "a32_write_performed": false,
      "a33_write_performed": false,
      "budgets": [
        50,
        150,
        300
      ],
      "comparison_index_only": true,
      "context_cluster_ids": [
        "sage6c::context_cluster::002",
        "sage6c::context_cluster::003",
        "sage6c::context_cluster::005"
      ],
      "context_snapshot_hashes": [
        "{\"digest\":\"2fd24ab52132f6bc\",\"game_state\":\"NOT_FINISHED\",\"levels_completed\":0,\"shape\":[64,64]}",
        "{\"digest\":\"cee711e164dcf771\",\"game_state\":\"NOT_FINISHED\",\"levels_completed\":0,\"shape\":[64,64]}",
        "{\"digest\":\"fd06017864128f48\",\"game_state\":\"NOT_FINISHED\",\"levels_completed\":0,\"shape\":[64,64]}"
      ],
      "control_action": "ACTION3",
      "control_effect_group_id": "sage6f::control_conditioned_effect_group::003",
      "cross_context_merge_performed": false,
      "cross_control_effect_merge_performed": false,
      "effect_direction": "neutral",
      "effect_size_max": 0.0,
      "effect_size_min": 0.0,
      "effect_size_spread": 0.0,
      "effect_sizes": [
        0.0,
        0.0,
        0.0
      ],
      "game_id": "wa30-ee6fef47",
      "group_counted_as_scientific_evidence": false,
      "hypothesis_family": "local_patch_change_candidate",
      "independent_contexts": 3,
      "metric": "local_patch_before_after",
      "observation_ids": [
        "sage6f::control_observation::004",
        "sage6f::control_observation::006",
        "sage6f::control_observation::009"
      ],
      "observations": 3,
      "raw_contradiction_events": 0,
      "raw_neutral_events": 3,
      "raw_support_events": 0,
      "revision_performed": false,
      "revision_status": "CANDIDATE_ONLY",
      "status": "UNRESOLVED",
      "support": 0,
      "target_action": "ACTION2",
      "truth_status": "NOT_EVALUATED_BY_SAGE_6F",
      "wrong_confirmations": 0
    }
  ],
  "cross_game_mechanics_imported": 0,
  "execution_performed": false,
  "gate": {
    "a32_frontier_matches_eligibility_without_verdict": true,
    "all_outputs_candidate_only": true,
    "all_sage6c_context_boundaries_preserved": true,
    "all_source_observations_consolidated_once": true,
    "control_action_identities_preserved_without_merge": true,
    "control_conditioned_groups_are_comparison_indexes_only": true,
    "neutral_replication_attached_to_original_context": true,
    "paired_control_comparisons_are_exact_and_context_preserving": true,
    "raw_event_accounting_exact": true,
    "source_registry_quarantine_preserved": true,
    "source_sage6c_gate_passed": true,
    "source_sage6e_gate_passed": true
  },
  "observation_records": [
    {
      "a32_write_performed": false,
      "a33_write_performed": false,
      "budget": 50,
      "context_snapshot_hash": "{\"digest\":\"762cdd46923302d2\",\"game_state\":\"NOT_FINISHED\",\"levels_completed\":0,\"shape\":[64,64]}",
      "contradiction_events": 0,
      "control_action": "ACTION1",
      "control_context_signature_verified": true,
      "control_signal": 32.0,
      "effect_direction": "neutral",
      "effect_size": 0.0,
      "game_id": "wa30-ee6fef47",
      "hypothesis_family": "local_patch_change_candidate",
      "live_prefix_replay_exact": true,
      "metric": "local_patch_before_after",
      "neutral_events": 1,
      "observation_id": "sage6f::control_observation::001",
      "protocol_execution_exact": true,
      "raw_event_counted_as_confirmation": false,
      "raw_event_counted_as_refutation": false,
      "raw_event_counted_as_scientific_support": false,
      "replication_role": "ORIGINAL_CONTROLLED_OBSERVATION",
      "revision_performed": false,
      "revision_status": "CANDIDATE_ONLY",
      "same_context_replication_is_independent_context": false,
      "source_context_cluster_id": "sage6c::context_cluster::001",
      "source_hypothesis_id": "sage6a::live_mini_frontier::050::0012",
      "source_record_id": "sage6c::controlled_event::001",
      "source_request_id": "m2m3::sage6a::live_mini_frontier::050::0012",
      "source_stage": "SAGE.6c",
      "source_step": 12,
      "source_transition_id": "sage6a::wa30-ee6fef47::budget_050::step_0012",
      "support": 0,
      "support_events": 0,
      "target_action": "ACTION2",
      "target_action_args": null,
      "target_context_signature_verified": true,
      "target_signal": 32.0,
      "truth_status": "NOT_EVALUATED_BY_SAGE_6F",
      "wrong_confirmations": 0
    },
    {
      "a32_write_performed": false,
      "a33_write_performed": false,
      "budget": 50,
      "context_snapshot_hash": "{\"digest\":\"762cdd46923302d2\",\"game_state\":\"NOT_FINISHED\",\"levels_completed\":0,\"shape\":[64,64]}",
      "contradiction_events": 0,
      "control_action": "ACTION1",
      "control_context_signature_verified": true,
      "control_signal": 32.0,
      "effect_direction": "neutral",
      "effect_size": 0.0,
      "game_id": "wa30-ee6fef47",
      "hypothesis_family": "local_patch_change_candidate",
      "live_prefix_replay_exact": true,
      "metric": "local_patch_before_after",
      "neutral_events": 1,
      "observation_id": "sage6f::control_observation::002",
      "protocol_execution_exact": true,
      "raw_event_counted_as_confirmation": false,
      "raw_event_counted_as_refutation": false,
      "raw_event_counted_as_scientific_support": false,
      "replication_role": "EXACT_NEUTRAL_CONTEXT_REPLICATION",
      "revision_performed": false,
      "revision_status": "CANDIDATE_ONLY",
      "same_context_replication_is_independent_context": false,
      "source_context_cluster_id": "sage6c::context_cluster::001",
      "source_hypothesis_id": "sage6a::live_mini_frontier::050::0012",
      "source_record_id": "sage6d::followup_protocol::neutral_replication::050",
      "source_request_id": "m2m3::sage6a::live_mini_frontier::050::0012",
      "source_stage": "SAGE.6e",
      "source_step": 12,
      "source_transition_id": "sage6a::wa30-ee6fef47::budget_050::step_0012",
      "support": 0,
      "support_events": 0,
      "target_action": "ACTION2",
      "target_action_args": null,
      "target_context_signature_verified": true,
      "target_signal": 32.0,
      "truth_status": "NOT_EVALUATED_BY_SAGE_6F",
      "wrong_confirmations": 0
    },
    {
      "a32_write_performed": false,
      "a33_write_performed": false,
      "budget": 50,
      "context_snapshot_hash": "{\"digest\":\"cee711e164dcf771\",\"game_state\":\"NOT_FINISHED\",\"levels_completed\":0,\"shape\":[64,64]}",
      "contradiction_events": 0,
      "control_action": "ACTION1",
      "control_context_signature_verified": true,
      "control_signal": 1.0,
      "effect_direction": "positive",
      "effect_size": 32.0,
      "game_id": "wa30-ee6fef47",
      "hypothesis_family": "local_patch_change_candidate",
      "live_prefix_replay_exact": true,
      "metric": "local_patch_before_after",
      "neutral_events": 0,
      "observation_id": "sage6f::control_observation::003",
      "protocol_execution_exact": true,
      "raw_event_counted_as_confirmation": false,
      "raw_event_counted_as_refutation": false,
      "raw_event_counted_as_scientific_support": false,
      "replication_role": "ORIGINAL_CONTROLLED_OBSERVATION",
      "revision_performed": false,
      "revision_status": "CANDIDATE_ONLY",
      "same_context_replication_is_independent_context": false,
      "source_context_cluster_id": "sage6c::context_cluster::002",
      "source_hypothesis_id": "sage6a::live_mini_frontier::050::0048",
      "source_record_id": "sage6c::controlled_event::002",
      "source_request_id": "m2m3::sage6a::live_mini_frontier::050::0048",
      "source_stage": "SAGE.6c",
      "source_step": 48,
      "source_transition_id": "sage6a::wa30-ee6fef47::budget_050::step_0048",
      "support": 0,
      "support_events": 1,
      "target_action": "ACTION2",
      "target_action_args": null,
      "target_context_signature_verified": true,
      "target_signal": 33.0,
      "truth_status": "NOT_EVALUATED_BY_SAGE_6F",
      "wrong_confirmations": 0
    },
    {
      "a32_write_performed": false,
      "a33_write_performed": false,
      "budget": 50,
      "context_snapshot_hash": "{\"digest\":\"cee711e164dcf771\",\"game_state\":\"NOT_FINISHED\",\"levels_completed\":0,\"shape\":[64,64]}",
      "contradiction_events": 0,
      "control_action": "ACTION3",
      "control_context_signature_verified": true,
      "control_signal": 33.0,
      "effect_direction": "neutral",
      "effect_size": 0.0,
      "game_id": "wa30-ee6fef47",
      "hypothesis_family": "local_patch_change_candidate",
      "live_prefix_replay_exact": true,
      "metric": "local_patch_before_after",
      "neutral_events": 1,
      "observation_id": "sage6f::control_observation::004",
      "protocol_execution_exact": true,
      "raw_event_counted_as_confirmation": false,
      "raw_event_counted_as_refutation": false,
      "raw_event_counted_as_scientific_support": false,
      "replication_role": "DISTINCT_CONTROL_FOLLOWUP",
      "revision_performed": false,
      "revision_status": "CANDIDATE_ONLY",
      "same_context_replication_is_independent_context": false,
      "source_context_cluster_id": "sage6c::context_cluster::002",
      "source_hypothesis_id": "sage6a::live_mini_frontier::050::0048",
      "source_record_id": "sage6d::followup_protocol::control_diversity::050",
      "source_request_id": "m2m3::sage6a::live_mini_frontier::050::0048",
      "source_stage": "SAGE.6e",
      "source_step": 48,
      "source_transition_id": "sage6a::wa30-ee6fef47::budget_050::step_0048",
      "support": 0,
      "support_events": 0,
      "target_action": "ACTION2",
      "target_action_args": null,
      "target_context_signature_verified": true,
      "target_signal": 33.0,
      "truth_status": "NOT_EVALUATED_BY_SAGE_6F",
      "wrong_confirmations": 0
    },
    {
      "a32_write_performed": false,
      "a33_write_performed": false,
      "budget": 150,
      "context_snapshot_hash": "{\"digest\":\"2fd24ab52132f6bc\",\"game_state\":\"NOT_FINISHED\",\"levels_completed\":0,\"shape\":[64,64]}",
      "contradiction_events": 0,
      "control_action": "ACTION1",
      "control_context_signature_verified": true,
      "control_signal": 1.0,
      "effect_direction": "positive",
      "effect_size": 32.0,
      "game_id": "wa30-ee6fef47",
      "hypothesis_family": "local_patch_change_candidate",
      "live_prefix_replay_exact": true,
      "metric": "local_patch_before_after",
      "neutral_events": 0,
      "observation_id": "sage6f::control_observation::005",
      "protocol_execution_exact": true,
      "raw_event_counted_as_confirmation": false,
      "raw_event_counted_as_refutation": false,
      "raw_event_counted_as_scientific_support": false,
      "replication_role": "ORIGINAL_CONTROLLED_OBSERVATION",
      "revision_performed": false,
      "revision_status": "CANDIDATE_ONLY",
      "same_context_replication_is_independent_context": false,
      "source_context_cluster_id": "sage6c::context_cluster::003",
      "source_hypothesis_id": "sage6a::live_mini_frontier::150::0132",
      "source_record_id": "sage6c::controlled_event::003",
      "source_request_id": "m2m3::sage6a::live_mini_frontier::150::0132",
      "source_stage": "SAGE.6c",
      "source_step": 132,
      "source_transition_id": "sage6a::wa30-ee6fef47::budget_150::step_0132",
      "support": 0,
      "support_events": 1,
      "target_action": "ACTION2",
      "target_action_args": null,
      "target_context_signature_verified": true,
      "target_signal": 33.0,
      "truth_status": "NOT_EVALUATED_BY_SAGE_6F",
      "wrong_confirmations": 0
    },
    {
      "a32_write_performed": false,
      "a33_write_performed": false,
      "budget": 150,
      "context_snapshot_hash": "{\"digest\":\"2fd24ab52132f6bc\",\"game_state\":\"NOT_FINISHED\",\"levels_completed\":0,\"shape\":[64,64]}",
      "contradiction_events": 0,
      "control_action": "ACTION3",
      "control_context_signature_verified": true,
      "control_signal": 33.0,
      "effect_direction": "neutral",
      "effect_size": 0.0,
      "game_id": "wa30-ee6fef47",
      "hypothesis_family": "local_patch_change_candidate",
      "live_prefix_replay_exact": true,
      "metric": "local_patch_before_after",
      "neutral_events": 1,
      "observation_id": "sage6f::control_observation::006",
      "protocol_execution_exact": true,
      "raw_event_counted_as_confirmation": false,
      "raw_event_counted_as_refutation": false,
      "raw_event_counted_as_scientific_support": false,
      "replication_role": "DISTINCT_CONTROL_FOLLOWUP",
      "revision_performed": false,
      "revision_status": "CANDIDATE_ONLY",
      "same_context_replication_is_independent_context": false,
      "source_context_cluster_id": "sage6c::context_cluster::003",
      "source_hypothesis_id": "sage6a::live_mini_frontier::150::0132",
      "source_record_id": "sage6d::followup_protocol::control_diversity::150",
      "source_request_id": "m2m3::sage6a::live_mini_frontier::150::0132",
      "source_stage": "SAGE.6e",
      "source_step": 132,
      "source_transition_id": "sage6a::wa30-ee6fef47::budget_150::step_0132",
      "support": 0,
      "support_events": 0,
      "target_action": "ACTION2",
      "target_action_args": null,
      "target_context_signature_verified": true,
      "target_signal": 33.0,
      "truth_status": "NOT_EVALUATED_BY_SAGE_6F",
      "wrong_confirmations": 0
    },
    {
      "a32_write_performed": false,
      "a33_write_performed": false,
      "budget": 150,
      "context_snapshot_hash": "{\"digest\":\"fc273c717dbdb25d\",\"game_state\":\"NOT_FINISHED\",\"levels_completed\":0,\"shape\":[64,64]}",
      "contradiction_events": 0,
      "control_action": "ACTION1",
      "control_context_signature_verified": true,
      "control_signal": 0.0,
      "effect_direction": "positive",
      "effect_size": 32.0,
      "game_id": "wa30-ee6fef47",
      "hypothesis_family": "local_patch_change_candidate",
      "live_prefix_replay_exact": true,
      "metric": "local_patch_before_after",
      "neutral_events": 0,
      "observation_id": "sage6f::control_observation::007",
      "protocol_execution_exact": true,
      "raw_event_counted_as_confirmation": false,
      "raw_event_counted_as_refutation": false,
      "raw_event_counted_as_scientific_support": false,
      "replication_role": "ORIGINAL_CONTROLLED_OBSERVATION",
      "revision_performed": false,
      "revision_status": "CANDIDATE_ONLY",
      "same_context_replication_is_independent_context": false,
      "source_context_cluster_id": "sage6c::context_cluster::004",
      "source_hypothesis_id": "sage6a::live_mini_frontier::150::0144",
      "source_record_id": "sage6c::controlled_event::004",
      "source_request_id": "m2m3::sage6a::live_mini_frontier::150::0144",
      "source_stage": "SAGE.6c",
      "source_step": 144,
      "source_transition_id": "sage6a::wa30-ee6fef47::budget_150::step_0144",
      "support": 0,
      "support_events": 1,
      "target_action": "ACTION2",
      "target_action_args": null,
      "target_context_signature_verified": true,
      "target_signal": 32.0,
      "truth_status": "NOT_EVALUATED_BY_SAGE_6F",
      "wrong_confirmations": 0
    },
    {
      "a32_write_performed": false,
      "a33_write_performed": false,
      "budget": 300,
      "context_snapshot_hash": "{\"digest\":\"fd06017864128f48\",\"game_state\":\"NOT_FINISHED\",\"levels_completed\":0,\"shape\":[64,64]}",
      "contradiction_events": 0,
      "control_action": "ACTION1",
      "control_context_signature_verified": true,
      "control_signal": 0.0,
      "effect_direction": "positive",
      "effect_size": 32.0,
      "game_id": "wa30-ee6fef47",
      "hypothesis_family": "local_patch_change_candidate",
      "live_prefix_replay_exact": true,
      "metric": "local_patch_before_after",
      "neutral_events": 0,
      "observation_id": "sage6f::control_observation::008",
      "protocol_execution_exact": true,
      "raw_event_counted_as_confirmation": false,
      "raw_event_counted_as_refutation": false,
      "raw_event_counted_as_scientific_support": false,
      "replication_role": "ORIGINAL_CONTROLLED_OBSERVATION",
      "revision_performed": false,
      "revision_status": "CANDIDATE_ONLY",
      "same_context_replication_is_independent_context": false,
      "source_context_cluster_id": "sage6c::context_cluster::005",
      "source_hypothesis_id": "sage6a::live_mini_frontier::300::0024",
      "source_record_id": "sage6c::controlled_event::005",
      "source_request_id": "m2m3::sage6a::live_mini_frontier::300::0024",
      "source_stage": "SAGE.6c",
      "source_step": 24,
      "source_transition_id": "sage6a::wa30-ee6fef47::budget_300::step_0024",
      "support": 0,
      "support_events": 1,
      "target_action": "ACTION2",
      "target_action_args": null,
      "target_context_signature_verified": true,
      "target_signal": 32.0,
      "truth_status": "NOT_EVALUATED_BY_SAGE_6F",
      "wrong_confirmations": 0
    },
    {
      "a32_write_performed": false,
      "a33_write_performed": false,
      "budget": 300,
      "context_snapshot_hash": "{\"digest\":\"fd06017864128f48\",\"game_state\":\"NOT_FINISHED\",\"levels_completed\":0,\"shape\":[64,64]}",
      "contradiction_events": 0,
      "control_action": "ACTION3",
      "control_context_signature_verified": true,
      "control_signal": 32.0,
      "effect_direction": "neutral",
      "effect_size": 0.0,
      "game_id": "wa30-ee6fef47",
      "hypothesis_family": "local_patch_change_candidate",
      "live_prefix_replay_exact": true,
      "metric": "local_patch_before_after",
      "neutral_events": 1,
      "observation_id": "sage6f::control_observation::009",
      "protocol_execution_exact": true,
      "raw_event_counted_as_confirmation": false,
      "raw_event_counted_as_refutation": false,
      "raw_event_counted_as_scientific_support": false,
      "replication_role": "DISTINCT_CONTROL_FOLLOWUP",
      "revision_performed": false,
      "revision_status": "CANDIDATE_ONLY",
      "same_context_replication_is_independent_context": false,
      "source_context_cluster_id": "sage6c::context_cluster::005",
      "source_hypothesis_id": "sage6a::live_mini_frontier::300::0024",
      "source_record_id": "sage6d::followup_protocol::control_diversity::300",
      "source_request_id": "m2m3::sage6a::live_mini_frontier::300::0024",
      "source_stage": "SAGE.6e",
      "source_step": 24,
      "source_transition_id": "sage6a::wa30-ee6fef47::budget_300::step_0024",
      "support": 0,
      "support_events": 0,
      "target_action": "ACTION2",
      "target_action_args": null,
      "target_context_signature_verified": true,
      "target_signal": 32.0,
      "truth_status": "NOT_EVALUATED_BY_SAGE_6F",
      "wrong_confirmations": 0
    },
    {
      "a32_write_performed": false,
      "a33_write_performed": false,
      "budget": 300,
      "context_snapshot_hash": "{\"digest\":\"d56ee8f2b81af1e5\",\"game_state\":\"NOT_FINISHED\",\"levels_completed\":0,\"shape\":[64,64]}",
      "contradiction_events": 0,
      "control_action": "ACTION1",
      "control_context_signature_verified": true,
      "control_signal": 0.0,
      "effect_direction": "positive",
      "effect_size": 32.0,
      "game_id": "wa30-ee6fef47",
      "hypothesis_family": "local_patch_change_candidate",
      "live_prefix_replay_exact": true,
      "metric": "local_patch_before_after",
      "neutral_events": 0,
      "observation_id": "sage6f::control_observation::010",
      "protocol_execution_exact": true,
      "raw_event_counted_as_confirmation": false,
      "raw_event_counted_as_refutation": false,
      "raw_event_counted_as_scientific_support": false,
      "replication_role": "ORIGINAL_CONTROLLED_OBSERVATION",
      "revision_performed": false,
      "revision_status": "CANDIDATE_ONLY",
      "same_context_replication_is_independent_context": false,
      "source_context_cluster_id": "sage6c::context_cluster::006",
      "source_hypothesis_id": "sage6a::live_mini_frontier::300::0036",
      "source_record_id": "sage6c::controlled_event::006",
      "source_request_id": "m2m3::sage6a::live_mini_frontier::300::0036",
      "source_stage": "SAGE.6c",
      "source_step": 36,
      "source_transition_id": "sage6a::wa30-ee6fef47::budget_300::step_0036",
      "support": 0,
      "support_events": 1,
      "target_action": "ACTION2",
      "target_action_args": null,
      "target_context_signature_verified": true,
      "target_signal": 32.0,
      "truth_status": "NOT_EVALUATED_BY_SAGE_6F",
      "wrong_confirmations": 0
    }
  ],
  "outcome_status": "SAGE_SECOND_UNKNOWN_GAME_CONTROL_DEPENDENCE_CONSOLIDATED_A32_REVIEW_ELIGIBLE_CANDIDATE_ONLY",
  "outcome_status_is_candidate_only": true,
  "paired_control_comparisons": [
    {
      "a32_write_performed": false,
      "a33_write_performed": false,
      "action1_control_signal": 1.0,
      "action1_controlled_effect_size": 32.0,
      "action1_observation_id": "sage6f::control_observation::003",
      "action3_control_signal": 33.0,
      "action3_controlled_effect_size": 0.0,
      "action3_observation_id": "sage6f::control_observation::004",
      "budget": 50,
      "candidate_status": "PAIRED_ACTION1_ACTION3_CONTROL_DEPENDENT_CONTEXT_CANDIDATE_ONLY",
      "context_cluster_id": "sage6c::context_cluster::002",
      "context_preserved": true,
      "context_snapshot_hash": "{\"digest\":\"cee711e164dcf771\",\"game_state\":\"NOT_FINISHED\",\"levels_completed\":0,\"shape\":[64,64]}",
      "control_identities_preserved": true,
      "control_signal_gap_action3_minus_action1": 32.0,
      "controlled_effect_gap_action1_minus_action3": 32.0,
      "game_id": "wa30-ee6fef47",
      "paired_comparison_counted_as_scientific_verdict": false,
      "paired_comparison_id": "sage6f::paired_control_comparison::001",
      "revision_performed": false,
      "revision_status": "CANDIDATE_ONLY",
      "source_step": 48,
      "status": "UNRESOLVED",
      "support": 0,
      "target_action": "ACTION2",
      "target_signal_action1_pair": 33.0,
      "target_signal_action3_pair": 33.0,
      "target_signal_reproduced_across_control_pairs": true,
      "truth_status": "NOT_EVALUATED_BY_SAGE_6F"
    },
    {
      "a32_write_performed": false,
      "a33_write_performed": false,
      "action1_control_signal": 1.0,
      "action1_controlled_effect_size": 32.0,
      "action1_observation_id": "sage6f::control_observation::005",
      "action3_control_signal": 33.0,
      "action3_controlled_effect_size": 0.0,
      "action3_observation_id": "sage6f::control_observation::006",
      "budget": 150,
      "candidate_status": "PAIRED_ACTION1_ACTION3_CONTROL_DEPENDENT_CONTEXT_CANDIDATE_ONLY",
      "context_cluster_id": "sage6c::context_cluster::003",
      "context_preserved": true,
      "context_snapshot_hash": "{\"digest\":\"2fd24ab52132f6bc\",\"game_state\":\"NOT_FINISHED\",\"levels_completed\":0,\"shape\":[64,64]}",
      "control_identities_preserved": true,
      "control_signal_gap_action3_minus_action1": 32.0,
      "controlled_effect_gap_action1_minus_action3": 32.0,
      "game_id": "wa30-ee6fef47",
      "paired_comparison_counted_as_scientific_verdict": false,
      "paired_comparison_id": "sage6f::paired_control_comparison::002",
      "revision_performed": false,
      "revision_status": "CANDIDATE_ONLY",
      "source_step": 132,
      "status": "UNRESOLVED",
      "support": 0,
      "target_action": "ACTION2",
      "target_signal_action1_pair": 33.0,
      "target_signal_action3_pair": 33.0,
      "target_signal_reproduced_across_control_pairs": true,
      "truth_status": "NOT_EVALUATED_BY_SAGE_6F"
    },
    {
      "a32_write_performed": false,
      "a33_write_performed": false,
      "action1_control_signal": 0.0,
      "action1_controlled_effect_size": 32.0,
      "action1_observation_id": "sage6f::control_observation::008",
      "action3_control_signal": 32.0,
      "action3_controlled_effect_size": 0.0,
      "action3_observation_id": "sage6f::control_observation::009",
      "budget": 300,
      "candidate_status": "PAIRED_ACTION1_ACTION3_CONTROL_DEPENDENT_CONTEXT_CANDIDATE_ONLY",
      "context_cluster_id": "sage6c::context_cluster::005",
      "context_preserved": true,
      "context_snapshot_hash": "{\"digest\":\"fd06017864128f48\",\"game_state\":\"NOT_FINISHED\",\"levels_completed\":0,\"shape\":[64,64]}",
      "control_identities_preserved": true,
      "control_signal_gap_action3_minus_action1": 32.0,
      "controlled_effect_gap_action1_minus_action3": 32.0,
      "game_id": "wa30-ee6fef47",
      "paired_comparison_counted_as_scientific_verdict": false,
      "paired_comparison_id": "sage6f::paired_control_comparison::003",
      "revision_performed": false,
      "revision_status": "CANDIDATE_ONLY",
      "source_step": 24,
      "status": "UNRESOLVED",
      "support": 0,
      "target_action": "ACTION2",
      "target_signal_action1_pair": 32.0,
      "target_signal_action3_pair": 32.0,
      "target_signal_reproduced_across_control_pairs": true,
      "truth_status": "NOT_EVALUATED_BY_SAGE_6F"
    }
  ],
  "paired_control_pattern_counted_as_scientific_verdict": false,
  "raw_events_counted_as_support": false,
  "refutation_performed": false,
  "revision_performed": false,
  "revision_status": "CANDIDATE_ONLY",
  "scope_generalization_performed": false,
  "source_sage6c_context": {
    "budgets": [
      50,
      150,
      300
    ],
    "game_id": "wa30-ee6fef47",
    "gate_passed": true,
    "outcome_status": "SAGE_SECOND_UNKNOWN_GAME_EVENTS_CONSOLIDATED_CANDIDATE_ONLY",
    "revision_status": "CANDIDATE_ONLY",
    "schema_version": "sage.second_unknown_game_event_consolidation.v1",
    "source_counted_as_scientific_support": false,
    "support": 0,
    "truth_status": "NOT_EVALUATED_BY_SAGE_6C"
  },
  "source_sage6e_context": {
    "budgets": [
      50,
      150,
      300
    ],
    "game_id": "wa30-ee6fef47",
    "gate_passed": true,
    "outcome_status": "SAGE_SECOND_UNKNOWN_GAME_FOLLOWUPS_EXECUTED_CANDIDATE_ONLY",
    "revision_status": "CANDIDATE_ONLY",
    "schema_version": "sage.second_unknown_game_followup_execution.v1",
    "source_counted_as_scientific_support": false,
    "support": 0,
    "truth_status": "NOT_EVALUATED_BY_SAGE_6E"
  },
  "source_scoped_mechanics_reused": 0,
  "status": "UNRESOLVED",
  "summary": {
    "a32_intake_requested": false,
    "a32_write_performed": false,
    "a33_write_performed": false,
    "action1_neutral_observations": 2,
    "action1_positive_contexts": 5,
    "action3_neutral_contexts": 3,
    "budgets": [
      50,
      150,
      300
    ],
    "candidate_a32_review_frontiers": 1,
    "candidate_status": "CONTROL_DEPENDENT_MULTI_BUDGET_WITH_REPLICATED_NEUTRAL_EXCEPTION_CANDIDATE_ONLY",
    "context_clusters": 6,
    "context_clusters_preserved": 6,
    "control_actions": [
      "ACTION1",
      "ACTION3"
    ],
    "control_conditioned_effect_groups": 3,
    "cross_context_merges_performed": 0,
    "cross_game_mechanics_imported": 0,
    "distinct_control_actions": 2,
    "eligibility_requirements_passed": 14,
    "eligibility_requirements_total": 14,
    "game_id": "wa30-ee6fef47",
    "gate_passed": true,
    "missing_eligibility_requirements": [],
    "negative_effect_events": 0,
    "observation_records": 10,
    "outcome_status": "SAGE_SECOND_UNKNOWN_GAME_CONTROL_DEPENDENCE_CONSOLIDATED_A32_REVIEW_ELIGIBLE_CANDIDATE_ONLY",
    "paired_control_budgets": [
      50,
      150,
      300
    ],
    "paired_control_contexts": 3,
    "paired_control_effect_gap_spread": 0.0,
    "paired_control_effect_gaps": [
      32.0,
      32.0,
      32.0
    ],
    "raw_contradiction_events": 0,
    "raw_neutral_events": 5,
    "raw_support_events": 5,
    "ready_for_A32_review": 1,
    "ready_for_A32_review_is_not_verdict": true,
    "replicated_neutral_contexts": 1,
    "revision_status": "CANDIDATE_ONLY",
    "source_sage6c_observations": 6,
    "source_sage6c_outcome_status": "SAGE_SECOND_UNKNOWN_GAME_EVENTS_CONSOLIDATED_CANDIDATE_ONLY",
    "source_sage6e_observations": 4,
    "source_sage6e_outcome_status": "SAGE_SECOND_UNKNOWN_GAME_FOLLOWUPS_EXECUTED_CANDIDATE_ONLY",
    "source_scoped_mechanics_reused": 0,
    "support": 0,
    "truth_status": "NOT_EVALUATED_BY_SAGE_6F",
    "wrong_confirmations": 0
  },
  "support": 0,
  "truth_status": "NOT_EVALUATED_BY_SAGE_6F",
  "wrong_confirmations": 0
}
